COPYING.txt
MANIFEST.in
README.rst
setup.py
asyncplot/__init__.py
asyncplot/client.py
asyncplot/example1.py
asyncplot/server.py
asyncplot/thread.py
asyncplot/threading_server.py
asyncplot.egg-info/PKG-INFO
asyncplot.egg-info/SOURCES.txt
asyncplot.egg-info/dependency_links.txt
asyncplot.egg-info/top_level.txt