Metadata-Version: 1.1
Name: asyncplot
Version: 0.1
Summary: Asynchronous client-server library for simple plotting.
Home-page: https://bitbucket.org/mforbes/asyncplot
Author: Michael McNeil Forbes, Katheryn Buble
Author-email: michael.forbes+python@gmail.com
License: BSD
Keywords: asynchronous,plotting,matplotlib
Platform: UNKNOWN
Classifier: Development Status :: 3 - Alpha
Classifier: Operating System :: OS Independent
Classifier: Topic :: Utilities
Classifier: License :: OSI Approved :: BSD License
